wsgiserve/__init__.py
wsgiserve/__main__.py
wsgiserve-0.1.1.dist-info/DESCRIPTION.rst
wsgiserve-0.1.1.dist-info/METADATA
wsgiserve-0.1.1.dist-info/RECORD
wsgiserve-0.1.1.dist-info/WHEEL
wsgiserve-0.1.1.dist-info/entry_points.txt
wsgiserve-0.1.1.dist-info/metadata.json
wsgiserve-0.1.1.dist-info/top_level.txt
