Metadata-Version: 2.0
Name: wsgiserve
Version: 0.1.1
Summary: a command to run wsgi application defined paste deploy configuration.
Home-page: https://github.com/aodag/wsgiserve
Author: Atsushi Odagiri
Author-email: aodagx@gmail.com
License: MIT
Platform: UNKNOWN
Requires-Dist: hupper
Requires-Dist: plaster
Requires-Dist: plaster-pastedeploy
Provides-Extra: testing
Requires-Dist: flake8; extra == 'testing'
Requires-Dist: pytest; extra == 'testing'
Requires-Dist: pytest-cov; extra == 'testing'
Requires-Dist: waitress; extra == 'testing'
